cand/__init__.py
cand/cand
cand/client.py
cand/config.py
cand/listener.py
cand/serialization.py
cand/talker.py
cand/util.py
opencan_cand-0.1.2.data/scripts/cand
opencan_cand-0.1.2.dist-info/LICENSE
opencan_cand-0.1.2.dist-info/METADATA
opencan_cand-0.1.2.dist-info/WHEEL
opencan_cand-0.1.2.dist-info/top_level.txt
opencan_cand-0.1.2.dist-info/RECORD
