Metadata-Version: 2.1
Name: opencan-cand
Version: 0.1.2
Summary: A fast and super useful daemon for decoding and encoding CAN messages.
Author-email: OpenCAN <info@opencan.org>
License: MPL-2.0
Project-URL: Homepage, https://github.com/opencan/cand
Keywords: cand,can,canbus,can bus
Requires-Python: >=3.9
License-File: LICENSE
Requires-Dist: cantools (>=37.0.7)
Requires-Dist: coloredlogs (>=15.0.1)
Requires-Dist: msgpack (>=1.0.3)
Requires-Dist: python-can (>=3.3.4)
Requires-Dist: redis (>=4.5.5)
